e2k/__init__.py
e2k/inference.py
e2k/models/accent.npz
e2k/models/model-c2k.npz
e2k/models/model-p2k.npz
e2k/models/ngram.json.zip
e2k-0.6.2.dist-info/licenses/LICENSE
e2k-0.6.2.dist-info/METADATA
e2k-0.6.2.dist-info/WHEEL
e2k-0.6.2.dist-info/top_level.txt
e2k-0.6.2.dist-info/RECORD
