Metadata-Version: 2.4
Name: e2k
Version: 0.6.2
Summary: A tool for automatic English to Katakana conversion
Author-email: Patchethium <asguftuikh@gmail.com>
Requires-Python: >=3.10
License-File: LICENSE
Requires-Dist: numpy<3.0,>=1.0
Provides-Extra: cpu
Requires-Dist: torch>=2.6.0; extra == "cpu"
Provides-Extra: cu121
Requires-Dist: torch>=2.5.0; extra == "cu121"
Provides-Extra: cu124
Requires-Dist: torch>=2.6.0; extra == "cu124"
Dynamic: license-file
